setup.py
ditto/__init__.py
ditto/test_ditto.py
ditto/test_module.py
ditto.egg-info/PKG-INFO
ditto.egg-info/SOURCES.txt
ditto.egg-info/dependency_links.txt
ditto.egg-info/requires.txt
ditto.egg-info/top_level.txt