Metadata-Version: 1.0
Name: ditto
Version: 1.2.4
Summary: Python Class Mocking Framework
Home-page: https://github.com/ironport/ditto
Author: Kyle Derr
Author-email: kyle.derr@gmail.com
License: UNKNOWN
Platform: UNKNOWN
